{
    "data": {
        "chiefBonus": {
            "1397016": [{
                    "chiefAvatarUrl": "http://p0.meituan.net/movie/4f1649fb5c2643e1d7851b819685f55f39051.jpg",
                    "chiefName": "朱一龙"
                },
                {
                    "chiefAvatarUrl": "http://p1.meituan.net/movie/b074d011bd2d6d89dbb7d0b8062e32e648461.jpg",
                    "chiefName": "杨恩又"
                }
            ],
            "1410425": [{
                    "chiefAvatarUrl": "http://p0.meituan.net/movie/876a62b75fe1d407721084f85ab0a81929475.jpg",
                    "chiefName": "张弛"
                },
                {
                    "chiefAvatarUrl": "http://p0.meituan.net/movie/3ce9831142af182367aeca557e5928d427961.jpg",
                    "chiefName": "周楠"
                },
                {
                    "chiefAvatarUrl": "http://p0.meituan.net/movie/cdfb1739d2d8341cd5c75b875338124b25545.jpg",
                    "chiefName": "饶晓志"
                }
            ]
        },
        "coming": [],
        "hot": [{
                "bingeWatch": 0,
                "boxInfo": "上映14天，累计票房67789万",
                "cat": "动作,冒险,科幻",
                "civilPubSt": 0,
                "comingTitle": "6月10日 周五",
                "desc": "主演:克里斯·帕拉特,布莱丝·达拉斯·霍华德,劳拉·邓恩",
                "dir": "科林·特雷沃罗",
                "dur": 147,
                "effectShowNum": 0,
                "followst": 0,
                "fra": "法国,阿根廷,澳大利亚,巴西,德国,韩国,荷兰,葡萄牙,斯洛伐克,乌克兰,保加利亚,加拿大,挪威,土耳其,美国,英国",
                "frt": "2022-06-10 00:00:00,2022-06-10 00:00:00,2022-06-10 00:00:00,2022-06-10 00:00:00,2022-06-10 00:00:00,2022-06-10 00:00:00,2022-06-10 00:00:00,2022-06-10 00:00:00,2022-06-10 00:00:00,2022-06-10 00:00:00,2022-06-10 00:00:00,2022-06-10 00:00:00,2022-06-10 00:00:00,2022-06-10 00:00:00,2022-06-10 00:00:00,2022-06-10 00:00:00",
                "globalReleased": true,
                "haspromotionTag": false,
                "headLineShow": false,
                "id": 1187439,
                "img": "https://p0.pipi.cn/mmdb/25bfd671be15bf51baf0ee3a5d06b91bf94c3.jpg?imageMogr2/thumbnail/2500x2500%3E",
                "isRevival": false,
                "late": false,
                "localPubSt": 0,
                "mark": false,
                "mk": 8,
                "movieType": 0,
                "nm": "侏罗纪世界3",
                "pn": 61,
                "preSale": 0,
                "preShow": false,
                "proScore": 0,
                "proScoreNum": 0,
                "pubDate": 1654790400000,
                "pubDesc": "2022-06-10中国大陆上映",
                "pubShowNum": 0,
                "recentShowDate": 1655913600000,
                "recentShowNum": 0,
                "rt": "2022-06-10",
                "sc": 8,
                "scm": "",
                "scoreLabel": "猫眼购票评分",
                "showCinemaNum": 221,
                "showInfo": "今天221家影院放映2906场",
                "showNum": 2906,
                "showStateButton": {
                    "color": "#F03D37",
                    "content": "购票",
                    "onlyPreShow": false
                },
                "showTimeInfo": "2022-06-10上映",
                "showst": 3,
                "snum": 136298,
                "star": "克里斯·帕拉特,布莱丝·达拉斯·霍华德,劳拉·邓恩",
                "totalShowNum": 6959,
                "ver": "IMAX 3D/IMAX 2D/杜比影院 2D/中国巨幕3D/中国巨幕2D/CINITY 3D/3D/2D/全景声",
                "videoId": 488017,
                "videoName": "《侏罗纪世界3》 终极预告重磅来袭 影史传奇史诗终章即将解锁",
                "videourl": "https://vod.pipi.cn/fec9203cvodtransbj1251246104/3d5cfd24387702301752506160/v.f42905.mp4",
                "vnum": 13,
                "vodPlay": false,
                "wish": 433283,
                "wishst": 0
            },
            {
                "bingeWatch": 0,
                "boxInfo": "喵，即将上映",
                "cat": "剧情,家庭",
                "civilPubSt": 0,
                "comingTitle": "6月24日 周五",
                "desc": "主演:朱一龙,杨恩又,王戈",
                "dir": "刘江江",
                "dur": 112,
                "effectShowNum": 1683,
                "followst": 0,
                "globalReleased": false,
                "haspromotionTag": false,
                "headLineShow": false,
                "id": 1397016,
                "img": "https://p0.pipi.cn/mmdb/25bfd671339c7e8ea33139d0476cb0d92908d.jpg?imageMogr2/thumbnail/2500x2500%3E",
                "isRevival": false,
                "late": false,
                "localPubSt": 0,
                "mark": false,
                "mk": 9.7,
                "movieType": 0,
                "nm": "人生大事",
                "pn": 90,
                "preSale": 1,
                "preShow": false,
                "proScore": 0,
                "proScoreNum": 0,
                "pubDate": 1656000000000,
                "pubDesc": "2022-06-24 18:00中国大陆上映",
                "pubShowNum": 1683,
                "recentShowDate": 1655913600000,
                "recentShowNum": 706,
                "rt": "2022-06-24",
                "sc": 9.7,
                "scm": "",
                "scoreLabel": "猫眼点映评分",
                "showCinemaNum": 111,
                "showInfo": "今天111家影院放映706场",
                "showNum": 706,
                "showStateButton": {
                    "color": "#3C9FE6",
                    "content": "预售",
                    "onlyPreShow": false
                },
                "showTimeInfo": "2022-06-24 本周五上映",
                "showst": 4,
                "snum": 24001,
                "star": "朱一龙,杨恩又,王戈",
                "totalShowNum": 6230,
                "ver": "中国巨幕2D/CINITY 2D/2D",
                "videoId": 488274,
                "videoName": "朱一龙主演电影《人生大事》发布创作特辑 监制韩延分享幕后故事真诚期许",
                "videourl": "https://vod.pipi.cn/fec9203cvodtransbj1251246104/fe820204387702302418410337/v.f42905.mp4",
                "vnum": 13,
                "vodPlay": false,
                "wish": 407594,
                "wishst": 0
            },
            {
                "bingeWatch": 0,
                "boxInfo": "上映6天，累计票房6820万",
                "cat": "剧情,青春",
                "civilPubSt": 0,
                "comingTitle": "6月18日 周六",
                "desc": "主演:赵今麦,林一,沈月",
                "dir": "林孝谦",
                "dur": 106,
                "effectShowNum": 0,
                "followst": 0,
                "globalReleased": true,
                "haspromotionTag": false,
                "headLineShow": false,
                "id": 1336701,
                "img": "https://p0.pipi.cn/mmdb/25bfd671b12f2ad7c3d7c37db5a7ce2aadac9.jpg?imageMogr2/thumbnail/2500x2500%3E",
                "isRevival": false,
                "late": false,
                "localPubSt": 0,
                "mark": false,
                "mk": 8.1,
                "movieType": 0,
                "nm": "一周的朋友",
                "pn": 51,
                "preSale": 0,
                "preShow": false,
                "proScore": 0,
                "proScoreNum": 0,
                "pubDate": 1655481600000,
                "pubDesc": "2022-06-18 09:00中国大陆上映",
                "pubShowNum": 0,
                "recentShowDate": 1655913600000,
                "recentShowNum": 0,
                "rt": "2022-06-18",
                "sc": 8.1,
                "scm": "@我最想见的朋友",
                "scoreLabel": "猫眼购票评分",
                "showCinemaNum": 214,
                "showInfo": "今天214家影院放映1055场",
                "showNum": 1055,
                "showStateButton": {
                    "color": "#F03D37",
                    "content": "购票",
                    "onlyPreShow": false
                },
                "showTimeInfo": "2022-06-18上映",
                "showst": 3,
                "snum": 33993,
                "star": "赵今麦,林一,沈月",
                "totalShowNum": 1858,
                "ver": "CINITY 2D/2D",
                "videoId": 488163,
                "videoName": "《一周的朋友》曝终极预告 明日上映揭晓赵今麦青春的秘密 ",
                "videourl": "https://vod.pipi.cn/fec9203cvodtransbj1251246104/752826c0387702302121563405/v.f42905.mp4",
                "vnum": 16,
                "vodPlay": false,
                "wish": 265284,
                "wishst": 0
            },
            {
                "bingeWatch": 0,
                "boxInfo": "上映22天，累计票房12966万",
                "cat": "爱情,青春",
                "civilPubSt": 0,
                "comingTitle": "6月2日 周四",
                "desc": "主演:张雪迎,辛云来,伍嘉成",
                "dir": "黄斌",
                "dur": 102,
                "effectShowNum": 0,
                "followst": 0,
                "globalReleased": true,
                "haspromotionTag": false,
                "headLineShow": false,
                "id": 1308364,
                "img": "https://p0.pipi.cn/mmdb/25bfd671be151b2ff711e5024a88733756aae.jpg?imageMogr2/thumbnail/2500x2500%3E",
                "isRevival": false,
                "late": false,
                "localPubSt": 0,
                "mark": false,
                "mk": 8.3,
                "movieType": 0,
                "nm": "暗恋·橘生淮南",
                "pn": 68,
                "preSale": 0,
                "preShow": false,
                "proScore": 0,
                "proScoreNum": 0,
                "pubDate": 1654099200000,
                "pubDesc": "2022-06-02 18:00中国大陆上映",
                "pubShowNum": 0,
                "recentShowDate": 1655913600000,
                "recentShowNum": 0,
                "rt": "2022-06-02",
                "sc": 8.3,
                "scm": "",
                "scoreLabel": "猫眼购票评分",
                "showCinemaNum": 151,
                "showInfo": "今天151家影院放映372场",
                "showNum": 372,
                "showStateButton": {
                    "color": "#F03D37",
                    "content": "购票",
                    "onlyPreShow": false
                },
                "showTimeInfo": "2022-06-02上映",
                "showst": 3,
                "snum": 53137,
                "star": "张雪迎,辛云来,伍嘉成",
                "totalShowNum": 533,
                "ver": "CINITY 2D/2D",
                "videoId": 487893,
                "videoName": "《暗恋·橘生淮南》“我们的十年”终极预告",
                "videourl": "https://vod.pipi.cn/fec9203cvodtransbj1251246104/27477d3a387702301558758565/v.f42905.mp4",
                "vnum": 14,
                "vodPlay": false,
                "wish": 297453,
                "wishst": 0
            },
            {
                "bingeWatch": 0,
                "boxInfo": "上映56天，累计票房31860万",
                "cat": "喜剧,动画,动作",
                "civilPubSt": 0,
                "comingTitle": "4月29日 周五",
                "desc": "主演:山姆·洛克威尔,秦昊,奥卡菲娜",
                "dir": "彼埃尔·佩里菲尔",
                "dur": 100,
                "effectShowNum": 0,
                "followst": 0,
                "fra": "荷兰,俄罗斯,立陶宛,拉脱维亚,瑞典,阿根廷,澳大利亚,巴西,加拿大,德国,爱尔兰,意大利,墨西哥,葡萄牙,新加坡,斯洛伐克,土耳其,美国",
                "frt": "2022-03-23,2022-03-24,2022-03-25,2022-03-25,2022-03-25,,,,,,,,,,,,2022-04-22,2022-04-22",
                "ftime": ",,,,,2022-04,2022-04,2022-04,2022-04,2022-04,2022-04,2022-04,2022-04,2022-04,2022-04,2022-04,,",
                "globalReleased": true,
                "haspromotionTag": false,
                "headLineShow": false,
                "id": 1298265,
                "img": "https://p0.pipi.cn/mmdb/25bfd67171f2ff338f31397eddc97451194d8.jpg?imageMogr2/thumbnail/2500x2500%3E",
                "isRevival": false,
                "late": false,
                "localPubSt": 0,
                "mark": false,
                "mk": 9.1,
                "movieType": 0,
                "nm": "坏蛋联盟",
                "pn": 4,
                "preSale": 0,
                "preShow": false,
                "proScore": 0,
                "proScoreNum": 0,
                "pubDate": 1651161600000,
                "pubDesc": "2022-04-29中国大陆上映",
                "pubShowNum": 0,
                "recentShowDate": 1655913600000,
                "recentShowNum": 0,
                "rt": "2022-04-29",
                "sc": 9.1,
                "scm": "",
                "scoreLabel": "猫眼购票评分",
                "showCinemaNum": 169,
                "showInfo": "今天169家影院放映433场",
                "showNum": 433,
                "showStateButton": {
                    "color": "#F03D37",
                    "content": "购票",
                    "onlyPreShow": false
                },
                "showTimeInfo": "2022-04-29上映",
                "showst": 3,
                "snum": 83773,
                "star": "山姆·洛克威尔,秦昊,奥卡菲娜",
                "totalShowNum": 803,
                "ver": "中国巨幕3D/CINITY 3D/3D",
                "videoId": 482951,
                "videoName": "梦工场全新IP《坏蛋联盟》发布新预告 好莱坞王牌阵容打造欢乐冒险",
                "videourl": "https://vod.pipi.cn/fec9203cvodtransbj1251246104/badd7131387702292918009405/v.f42905.mp4",
                "vnum": 6,
                "vodPlay": false,
                "wish": 25245,
                "wishst": 0
            },
            {
                "bingeWatch": 0,
                "boxInfo": "上映14天，累计票房1010万",
                "cat": "剧情,悬疑,犯罪",
                "civilPubSt": 0,
                "comingTitle": "6月10日 周五",
                "desc": "主演:丹尼尔·雷德克里夫,丹尼尔·韦伯,伊恩·哈特",
                "dir": "弗朗西斯·安南",
                "dur": 106,
                "effectShowNum": 0,
                "followst": 0,
                "fra": "英国,阿拉伯联合酋长国,黎巴嫩,卡塔尔,沙特阿拉伯,英国,意大利,美国,俄罗斯,加拿大,西班牙,西班牙,波兰,中国台湾,韩国,澳大利亚,爱沙尼亚,菲律宾,澳大利亚,新加坡,墨西哥,瑞典,芬兰,荷兰,土耳其,法国,日本,巴西,阿根廷,爱沙尼亚,哈萨克斯坦,德国,德国,葡萄牙,印度尼西亚,挪威,以色列",
                "frt": "2020-02-29 00:00:00,2020-03-05 00:00:00,2020-03-05 00:00:00,2020-03-05 00:00:00,2020-03-05 00:00:00,2020-03-06 00:00:00,2020-03-06 00:00:00,2020-03-06 00:00:00,2020-03-26 00:00:00,2020-04-07 00:00:00,2020-04-08 00:00:00,2020-04-08 00:00:00,2020-04-10 00:00:00,2020-04-17 00:00:00,2020-05-06 00:00:00,2020-05-22 00:00:00,2020-06-19 00:00:00,2020-06-24 00:00:00,2020-07-11 00:00:00,2020-07-13 00:00:00,2020-07-17 00:00:00,2020-07-20 00:00:00,2020-07-22 00:00:00,2020-08-07 00:00:00,2020-09-04 00:00:00,2020-09-09 00:00:00,2020-09-18 00:00:00,2020-10-01 00:00:00,2020-10-26 00:00:00,,2020-11-05 00:00:00,2020-11-19 00:00:00,2020-11-26 00:00:00,2020-12-10 00:00:00,2021-01-20 00:00:00,2021-03-26 00:00:00,2022-04-07 00:00:00",
                "ftime": ",,,,,,,,,,,,,,,,,,,,,,,,,,,,,2020-11,,,,,,,",
                "globalReleased": true,
                "haspromotionTag": false,
                "headLineShow": false,
                "id": 1205957,
                "img": "https://p0.pipi.cn/mmdb/25bfd687ecdc7e2ff7af339b7138f3b0d2d70.jpg?imageMogr2/thumbnail/2500x2500%3E",
                "isRevival": false,
                "late": false,
                "localPubSt": 0,
                "mark": false,
                "mk": 7.8,
                "movieType": 0,
                "nm": "天才计划",
                "pn": 39,
                "preSale": 0,
                "preShow": false,
                "proScore": 0,
                "proScoreNum": 0,
                "pubDate": 1654790400000,
                "pubDesc": "2022-06-10中国大陆上映",
                "pubShowNum": 0,
                "recentShowDate": 1655913600000,
                "recentShowNum": 0,
                "rt": "2022-06-10",
                "sc": 7.8,
                "scm": "",
                "scoreLabel": "猫眼购票评分",
                "showCinemaNum": 119,
                "showInfo": "今天119家影院放映297场",
                "showNum": 297,
                "showStateButton": {
                    "color": "#F03D37",
                    "content": "购票",
                    "onlyPreShow": false
                },
                "showTimeInfo": "2022-06-10上映",
                "showst": 3,
                "snum": 2525,
                "star": "丹尼尔·雷德克里夫,丹尼尔·韦伯,伊恩·哈特",
                "totalShowNum": 462,
                "ver": "2D",
                "videoId": 487880,
                "videoName": "电影《天才计划》定档6月10日 “哈利·波特”上演超激越狱大秀",
                "videourl": "https://vod.pipi.cn/fec9203cvodtransbj1251246104/b4eb2084387702301502428452/v.f42905.mp4",
                "vnum": 3,
                "vodPlay": false,
                "wish": 5638,
                "wishst": 0
            },
            {
                "bingeWatch": 0,
                "boxInfo": "上映143天，累计票房262766万",
                "cat": "喜剧",
                "civilPubSt": 0,
                "comingTitle": "2月1日 周二",
                "desc": "主演:马丽,魏翔,陈明昊",
                "dir": "邢文雄",
                "dur": 109,
                "effectShowNum": 0,
                "followst": 0,
                "globalReleased": true,
                "haspromotionTag": false,
                "headLineShow": false,
                "id": 1433696,
                "img": "https://p0.pipi.cn/mmdb/25bfd67171f51bbe2a338ff481e40c341deee.jpg?imageMogr2/thumbnail/2500x2500%3E",
                "isRevival": false,
                "late": false,
                "localPubSt": 0,
                "mark": false,
                "mk": 9.1,
                "movieType": 0,
                "nm": "这个杀手不太冷静",
                "pn": 139,
                "preSale": 0,
                "preShow": false,
                "proScore": 0,
                "proScoreNum": 0,
                "pubDate": 1643644800000,
                "pubDesc": "2022-02-01 08:00中国大陆上映",
                "pubShowNum": 0,
                "recentShowDate": 1655913600000,
                "recentShowNum": 0,
                "rt": "2022-02-01",
                "sc": 9.1,
                "scm": "爆笑喜剧持续热映，马丽魏翔笑不停",
                "scoreLabel": "猫眼购票评分",
                "showCinemaNum": 25,
                "showInfo": "今天25家影院放映53场",
                "showNum": 53,
                "showStateButton": {
                    "color": "#F03D37",
                    "content": "购票",
                    "onlyPreShow": false
                },
                "showTimeInfo": "2022-02-01上映",
                "showst": 3,
                "snum": 584465,
                "star": "马丽,魏翔,陈明昊",
                "totalShowNum": 77,
                "ver": "杜比影院 2D/中国巨幕2D/CINITY 2D/2D/4DX",
                "videoId": 484757,
                "videoName": "《这个杀手不太冷静》“好梦成真”版预告真挚上线引人共情",
                "videourl": "https://vod.pipi.cn/fec9203cvodtransbj1251246104/4a5df776387702295472626209/v.f42905.mp4",
                "vnum": 15,
                "vodPlay": false,
                "wish": 555706,
                "wishst": 0
            },
            {
                "bingeWatch": 0,
                "boxInfo": "上映91天，累计票房15838万",
                "cat": "灾难,科幻",
                "civilPubSt": 0,
                "comingTitle": "3月25日 周五",
                "desc": "主演:哈莉·贝瑞,帕特里克·威尔森,约翰·布莱德利",
                "dir": "罗兰·艾默里奇",
                "dur": 130,
                "effectShowNum": 0,
                "followst": 0,
                "fra": "阿根廷,奥地利,澳大利亚,巴西,捷克,德国,中国香港,意大利,马来西亚,荷兰,新西兰,葡萄牙,俄罗斯,瑞典,新加坡,斯洛伐克,乌克兰,保加利亚,加拿大,西班牙,英国,爱尔兰,印度,立陶宛,波兰,土耳其,美国,法国,博茨瓦纳,丹麦,阿尔巴尼亚",
                "frt": "2022-02-03 00:00:00,2022-02-03 00:00:00,2022-02-03 00:00:00,2022-02-03 00:00:00,2022-02-03 00:00:00,2022-02-03 00:00:00,2022-02-03 00:00:00,2022-02-03 00:00:00,2022-02-03 00:00:00,2022-02-03 00:00:00,2022-02-03 00:00:00,2022-02-03 00:00:00,2022-02-03 00:00:00,2022-02-03 00:00:00,2022-02-03 00:00:00,2022-02-03 00:00:00,2022-02-03 00:00:00,2022-02-04 00:00:00,2022-02-04 00:00:00,2022-02-04 00:00:00,2022-02-04 00:00:00,2022-02-04 00:00:00,2022-02-04 00:00:00,2022-02-04 00:00:00,2022-02-04 00:00:00,2022-02-04 00:00:00,2022-02-04 00:00:00,2022-02-09 00:00:00,2022-02-13 00:00:00,2022-02-24 00:00:00,2022-02-26 00:00:00",
                "globalReleased": true,
                "haspromotionTag": false,
                "headLineShow": false,
                "id": 1048263,
                "img": "https://p0.pipi.cn/mmdb/25bfd69adddddd8ea3af33d441fff7dde177e.jpg?imageMogr2/thumbnail/2500x2500%3E",
                "isRevival": false,
                "late": false,
                "localPubSt": 0,
                "mark": false,
                "mk": 8.2,
                "movieType": 0,
                "nm": "月球陨落",
                "pn": 44,
                "preSale": 0,
                "preShow": false,
                "proScore": 0,
                "proScoreNum": 0,
                "pubDate": 1648137600000,
                "pubDesc": "2022-03-25 10:00中国大陆上映",
                "pubShowNum": 0,
                "recentShowDate": 1655913600000,
                "recentShowNum": 0,
                "rt": "2022-03-25",
                "sc": 8.2,
                "scm": "",
                "scoreLabel": "猫眼购票评分",
                "showCinemaNum": 28,
                "showInfo": "今天28家影院放映42场",
                "showNum": 42,
                "showStateButton": {
                    "color": "#F03D37",
                    "content": "购票",
                    "onlyPreShow": false
                },
                "showTimeInfo": "2022-03-25上映",
                "showst": 3,
                "snum": 58735,
                "star": "哈莉·贝瑞,帕特里克·威尔森,约翰·布莱德利",
                "totalShowNum": 49,
                "ver": "IMAX 2D/杜比影院 2D/中国巨幕2D/CINITY 2D/2D/全景声",
                "videoId": 486255,
                "videoName": "强特效！硬科幻！深情感！灾难巨制《月球陨落》强势占领清明假期",
                "videourl": "https://vod.pipi.cn/fec9203cvodtransbj1251246104/dbe81c9c387702298436751924/v.f42905.mp4",
                "vnum": 19,
                "vodPlay": false,
                "wish": 143238,
                "wishst": 0
            },
            {
                "bingeWatch": 0,
                "boxInfo": "喵，即将上映",
                "cat": "剧情",
                "civilPubSt": 0,
                "comingTitle": "7月1日 周五",
                "desc": "主演:周冬雨,尹昉,宋小宝",
                "dir": "周楠,张弛,田羽生,董越,饶晓志",
                "dur": 122,
                "effectShowNum": 437,
                "followst": 0,
                "globalReleased": false,
                "haspromotionTag": false,
                "headLineShow": false,
                "id": 1410425,
                "img": "https://p0.pipi.cn/mmdb/25bfd6719ab339b860af333d9ae02439e6179.jpg?imageMogr2/thumbnail/2500x2500%3E",
                "isRevival": false,
                "late": false,
                "localPubSt": 0,
                "mark": false,
                "mk": 0,
                "movieType": 0,
                "nm": "你是我的春天",
                "pn": 115,
                "preSale": 1,
                "preShow": false,
                "proScore": 0,
                "proScoreNum": 0,
                "pubDate": 1656604800000,
                "pubDesc": "2022-07-01 17:00中国大陆上映",
                "pubShowNum": 437,
                "recentShowDate": 1656604800000,
                "recentShowNum": 0,
                "rt": "2022-07-01",
                "sc": 0,
                "scm": "群星云集 献给每一个了不起的你",
                "scoreLabel": "暂无评分",
                "showCinemaNum": 0,
                "showInfo": "2022-07-01 下周五上映",
                "showNum": 0,
                "showStateButton": {
                    "color": "#3C9FE6",
                    "content": "预售",
                    "onlyPreShow": false
                },
                "showTimeInfo": "2022-07-01 下周五上映",
                "showst": 4,
                "snum": 830,
                "star": "周冬雨,尹昉,宋小宝",
                "totalShowNum": 647,
                "ver": "CINITY 2D/2D",
                "videoId": 488162,
                "videoName": "《你是我的春天》“社区老王”vlog",
                "videourl": "https://vod.pipi.cn/fec9203cvodtransbj1251246104/df6a6204387702302112991413/v.f42905.mp4",
                "vnum": 13,
                "vodPlay": false,
                "wish": 108540,
                "wishst": 0
            },
            {
                "bingeWatch": 0,
                "boxInfo": "上映27天，累计票房8094万",
                "cat": "冒险,动画",
                "civilPubSt": 0,
                "comingTitle": "5月28日 周六",
                "desc": "主演:哆啦A梦,水田山葵,大雄",
                "dir": "山口晋",
                "dur": 109,
                "effectShowNum": 0,
                "followst": 0,
                "fra": "日本",
                "frt": "2022-03-04",
                "globalReleased": true,
                "haspromotionTag": false,
                "headLineShow": false,
                "id": 1372606,
                "img": "https://p0.pipi.cn/mmdb/25bfd687b5351b87a9b5356cb3df409d810a0.jpg?imageMogr2/thumbnail/2500x2500%3E",
                "isRevival": false,
                "late": false,
                "localPubSt": 0,
                "mark": false,
                "mk": 8.4,
                "movieType": 0,
                "nm": "哆啦A梦：大雄的宇宙小战争 2021",
                "pn": 16,
                "preSale": 0,
                "preShow": false,
                "proScore": 0,
                "proScoreNum": 0,
                "pubDate": 1653667200000,
                "pubDesc": "2022-05-28 08:00中国大陆上映",
                "pubShowNum": 0,
                "recentShowDate": 1655913600000,
                "recentShowNum": 0,
                "rt": "2022-05-28",
                "sc": 8.4,
                "scm": "",
                "scoreLabel": "猫眼购票评分",
                "showCinemaNum": 90,
                "showInfo": "今天90家影院放映157场",
                "showNum": 157,
                "showStateButton": {
                    "color": "#F03D37",
                    "content": "购票",
                    "onlyPreShow": false
                },
                "showTimeInfo": "2022-05-28上映",
                "showst": 3,
                "snum": 17838,
                "star": "哆啦A梦,水田山葵,大雄",
                "totalShowNum": 303,
                "ver": "2D",
                "videoId": 488001,
                "videoName": "哆啦A梦剧场版曝首支预告 没有哆啦A梦的儿童节是不完整的",
                "videourl": "https://vod.pipi.cn/fec9203cvodtransbj1251246104/3d043480387702301711402940/v.f42905.mp4",
                "vnum": 6,
                "vodPlay": false,
                "wish": 39809,
                "wishst": 0
            },
            {
                "bingeWatch": 0,
                "boxInfo": "上映83天，累计票房7591万",
                "cat": "惊悚,动作,悬疑",
                "civilPubSt": 0,
                "comingTitle": "4月2日 周六",
                "desc": "主演:泰勒·拉塞尔,洛根·米勒,霍兰·罗登",
                "dir": "亚当·罗比特尔",
                "dur": 88,
                "effectShowNum": 0,
                "followst": 0,
                "fra": "澳大利亚,冰岛,葡萄牙,俄罗斯,新加坡,斯洛伐克,加拿大,英国,爱尔兰,立陶宛,瑞典,土耳其,美国,德国,荷兰,西班牙",
                "frt": "2021-07-01,2021-07-14,2021-07-15,2021-07-15,2021-07-15,2021-07-15,2021-07-16,2021-07-16,2021-07-16,2021-07-16,2021-07-16,2021-07-16,2021-07-16,2021-07-22,2021-07-22,2021-07-30",
                "globalReleased": true,
                "haspromotionTag": false,
                "headLineShow": false,
                "id": 1298049,
                "img": "https://p0.pipi.cn/mmdb/25bfd69a030338ddd2300b1f3b191305438ba.jpg?imageMogr2/thumbnail/2500x2500%3E",
                "isRevival": false,
                "late": false,
                "localPubSt": 0,
                "mark": false,
                "mk": 8.3,
                "movieType": 0,
                "nm": "密室逃生2",
                "pn": 95,
                "preSale": 0,
                "preShow": false,
                "proScore": 0,
                "proScoreNum": 0,
                "pubDate": 1648828800000,
                "pubDesc": "2022-04-02 18:00中国大陆上映",
                "pubShowNum": 0,
                "recentShowDate": 1655913600000,
                "recentShowNum": 0,
                "rt": "2022-04-02",
                "sc": 8.3,
                "scm": "",
                "scoreLabel": "猫眼购票评分",
                "showCinemaNum": 31,
                "showInfo": "今天31家影院放映57场",
                "showNum": 57,
                "showStateButton": {
                    "color": "#F03D37",
                    "content": "购票",
                    "onlyPreShow": false
                },
                "showTimeInfo": "2022-04-02上映",
                "showst": 3,
                "snum": 24176,
                "star": "泰勒·拉塞尔,洛根·米勒,霍兰·罗登",
                "totalShowNum": 93,
                "ver": "中国巨幕2D/2D",
                "videoId": 486257,
                "videoName": "明日上映！《密室逃生2》曝“酸雨街道”片段，让人心惊又抓狂",
                "videourl": "https://vod.pipi.cn/fec9203cvodtransbj1251246104/8437e453387702298442096232/v.f42905.mp4",
                "vnum": 17,
                "vodPlay": false,
                "wish": 40149,
                "wishst": 0
            },
            {
                "bingeWatch": 0,
                "boxInfo": "上映35天，累计票房1247万",
                "cat": "剧情,爱情",
                "civilPubSt": 0,
                "comingTitle": "5月20日 周五",
                "desc": "主演:米歇尔·道克瑞,休·博纳维尔,伊丽莎白·麦戈文",
                "dir": "西蒙·柯蒂斯",
                "dur": 119,
                "effectShowNum": 0,
                "followst": 0,
                "fra": "加拿大,德国,拉脱维亚,阿根廷,奥地利,匈牙利,荷兰,新西兰,葡萄牙,塞尔维亚,俄罗斯,保加利亚,西班牙,芬兰,英国,爱尔兰,立陶宛,挪威,瑞典,土耳其,美国,丹麦,意大利,冰岛,新加坡",
                "frt": ",,2022-03-15,2022-03-17,2022-03-17,2022-03-17,2022-03-17,2022-03-17,2022-03-17,2022-03-17,2022-03-17,2022-03-18,2022-03-18,2022-03-18,2022-04-29,2022-03-18,2022-03-18,2022-03-18,2022-03-18,2022-03-18,2022-05-20,2022-03-24,2022-03-24,2022-03-25,2022-04-28",
                "ftime": "2022-03,2022-03,,,,,,,,,,,,,,,,,,,,,,,",
                "globalReleased": true,
                "haspromotionTag": false,
                "headLineShow": false,
                "id": 1324996,
                "img": "https://p0.pipi.cn/mmdb/25bfd6877a3c692c9517893eb18848de814d8.jpg?imageMogr2/thumbnail/2500x2500%3E",
                "isRevival": false,
                "late": false,
                "localPubSt": 0,
                "mark": false,
                "mk": 8.8,
                "movieType": 0,
                "nm": "唐顿庄园2",
                "pn": 68,
                "preSale": 0,
                "preShow": false,
                "proScore": 0,
                "proScoreNum": 0,
                "pubDate": 1652976000000,
                "pubDesc": "2022-05-20中国大陆上映",
                "pubShowNum": 0,
                "recentShowDate": 1655913600000,
                "recentShowNum": 0,
                "rt": "2022-05-20",
                "sc": 8.8,
                "scm": "",
                "scoreLabel": "猫眼购票评分",
                "showCinemaNum": 13,
                "showInfo": "今天13家影院放映31场",
                "showNum": 31,
                "showStateButton": {
                    "color": "#F03D37",
                    "content": "购票",
                    "onlyPreShow": false
                },
                "showTimeInfo": "2022-05-20上映",
                "showst": 3,
                "snum": 4261,
                "star": "米歇尔·道克瑞,休·博纳维尔,伊丽莎白·麦戈文",
                "totalShowNum": 41,
                "ver": "杜比影院 2D/中国巨幕2D/CINITY 2D/2D/全景声",
                "videoId": 487780,
                "videoName": "丰富服饰炫彩夺目！《唐顿庄园2》斩获全平台好评无数",
                "videourl": "https://vod.pipi.cn/fec9203cvodtransbj1251246104/6cbeb281387702301304702364/v.f42905.mp4",
                "vnum": 9,
                "vodPlay": false,
                "wish": 23404,
                "wishst": 0
            }
        ],
        "movieIds": [
            1187439,
            1397016,
            1336701,
            1308364,
            1298265,
            1205957,
            1433696,
            1048263,
            1410425,
            1372606,
            1298049,
            1324996,
            1263216,
            1359726,
            1430937,
            346174,
            522013,
            1446115,
            1285096,
            1287309,
            1383307,
            1277549,
            1203439,
            1426819,
            1395465,
            1297952,
            1328693,
            1328765,
            1299976,
            1302341,
            1424470,
            1393881,
            1356218,
            1445469,
            344558,
            1250907,
            1338984,
            1276254,
            1299144,
            1367251,
            1336452,
            1442177,
            1413143
        ],
        "schemaUrl": "maoyan://maoyan.com/filmlist?index=onshow",
        "stid": "576591972453269000",
        "stids": [{
                "movieId": 1187439,
                "stid": "576591972453269000_a1187439_c0"
            },
            {
                "movieId": 1397016,
                "stid": "576591972453269000_a1397016_c1"
            },
            {
                "movieId": 1336701,
                "stid": "576591972453269000_a1336701_c2"
            },
            {
                "movieId": 1308364,
                "stid": "576591972453269000_a1308364_c3"
            },
            {
                "movieId": 1298265,
                "stid": "576591972453269000_a1298265_c4"
            },
            {
                "movieId": 1205957,
                "stid": "576591972453269000_a1205957_c5"
            },
            {
                "movieId": 1433696,
                "stid": "576591972453269000_a1433696_c6"
            },
            {
                "movieId": 1048263,
                "stid": "576591972453269000_a1048263_c7"
            },
            {
                "movieId": 1410425,
                "stid": "576591972453269000_a1410425_c8"
            },
            {
                "movieId": 1372606,
                "stid": "576591972453269000_a1372606_c9"
            },
            {
                "movieId": 1298049,
                "stid": "576591972453269000_a1298049_c10"
            },
            {
                "movieId": 1324996,
                "stid": "576591972453269000_a1324996_c11"
            }
        ],
        "total": 43
    }
}